{
  "type": "pivot",
  "neverRecomputeExistingPartitions": false,
  "optionalDependencies": false,
  "customMeta": {
    "kv": {}
  },
  "redispatchPartitioning": false,
  "maxRunningActivities": 0,
  "variables": {},
  "dkuProperties": [],
  "inputs": {
    "main": {
      "items": [
        {
          "ref": "ytrain_NpxebDC",
          "deps": []
        }
      ]
    }
  },
  "outputs": {
    "main": {
      "items": [
        {
          "ref": "ytrain_NpxebDC_by_timestamp",
          "appendMode": false
        }
      ]
    }
  },
  "labels": [],
  "versionTag": {
    "versionNumber": 0,
    "lastModifiedBy": {
      "login": "jtobelem"
    },
    "lastModifiedOn": 1633678901484
  },
  "creationTag": {
    "versionNumber": 0,
    "lastModifiedBy": {
      "login": "jtobelem"
    },
    "lastModifiedOn": 1633678901484
  },
  "tags": [],
  "customFields": {},
  "checklists": {
    "checklists": []
  }
}