{
  "type": "join",
  "neverRecomputeExistingPartitions": false,
  "optionalDependencies": false,
  "customMeta": {
    "kv": {}
  },
  "redispatchPartitioning": false,
  "maxRunningActivities": 0,
  "variables": {},
  "dkuProperties": [],
  "inputs": {
    "main": {
      "items": [
        {
          "ref": "ytrain_long_db",
          "deps": []
        },
        {
          "ref": "info_static_prepared_db",
          "deps": []
        }
      ]
    }
  },
  "outputs": {
    "main": {
      "items": [
        {
          "ref": "ytrain_long_db_joined",
          "appendMode": false
        }
      ]
    }
  },
  "labels": [],
  "versionTag": {
    "versionNumber": 1,
    "lastModifiedBy": {
      "login": "jtobelem"
    },
    "lastModifiedOn": 1633681036310
  },
  "creationTag": {
    "versionNumber": 0,
    "lastModifiedBy": {
      "login": "jtobelem"
    },
    "lastModifiedOn": 1633680930195
  },
  "tags": [],
  "customFields": {},
  "checklists": {
    "checklists": []
  }
}